{
  "annotations": {
    "list": [
      {
        "builtIn": 1,
        "datasource": "-- Grafana --",
        "enable": true,
        "hide": true,
        "iconColor": "rgba(0, 211, 255, 1)",
        "name": "Annotations & Alerts",
        "target": {
          "limit": 100,
          "matchAny": false,
          "tags": [],
          "type": "dashboard"
        },
        "type": "dashboard"
      }
    ]
  },
  "editable": true,
  "fiscalYearStartMonth": 0,
  "gnetId": null,
  "graphTooltip": 0,
  "links": [],
  "liveNow": false,
  "panels": [
    {
      "collapsed": false,
      "datasource": null,
      "gridPos": {
        "h": 1,
        "w": 24,
        "x": 0,
        "y": 0
      },
      "id": 12,
      "panels": [],
      "title": "Server Health",
      "type": "row"
    },
    {
      "datasource": null,
      "fieldConfig": {
        "defaults": {
          "color": {
            "mode": "thresholds"
          },
          "mappings": [
            {
              "options": {
                "0": {
                  "index": 0,
                  "text": "Down"
                },
                "1": {
                  "index": 1,
                  "text": "Up"
                }
              },
              "type": "value"
            }
          ],
          "thresholds": {
            "mode": "absolute",
            "steps": [
              {
                "color": "dark-red",
                "value": null
              },
              {
                "color": "green",
                "value": 1
              }
            ]
          }
        },
        "overrides": []
      },
      "gridPos": {
        "h": 7,
        "w": 4,
        "x": 0,
        "y": 1
      },
      "id": 33,
      "options": {
        "colorMode": "background",
        "graphMode": "area",
        "justifyMode": "auto",
        "orientation": "horizontal",
        "reduceOptions": {
          "calcs": [
            "lastNotNull"
          ],
          "fields": "",
          "values": false
        },
        "text": {},
        "textMode": "auto"
      },
      "pluginVersion": "8.2.1",
      "targets": [
        {
          "exemplar": true,
          "expr": "kube_pod_container_status_ready{container=\"postgres\",namespace=~\"$namespace\",pod=~\"$cluster-.*\"}",
          "instant": true,
          "interval": "",
          "legendFormat": "{{pod}}",
          "refId": "A"
        }
      ],
      "title": "Cluster Status",
      "type": "stat"
    },
    {
      "datasource": null,
      "fieldConfig": {
        "defaults": {
          "color": {
            "mode": "thresholds"
          },
          "mappings": [
            {
              "options": {
                "0": {
                  "index": 0,
                  "text": "No"
                },
                "1": {
                  "index": 1,
                  "text": "Yes"
                }
              },
              "type": "value"
            }
          ],
          "thresholds": {
            "mode": "absolute",
            "steps": [
              {
                "color": "dark-red",
                "value": null
              },
              {
                "color": "green",
                "value": 1
              }
            ]
          }
        },
        "overrides": []
      },
      "gridPos": {
        "h": 7,
        "w": 4,
        "x": 4,
        "y": 1
      },
      "id": 60,
      "options": {
        "colorMode": "background",
        "graphMode": "area",
        "justifyMode": "auto",
        "orientation": "horizontal",
        "reduceOptions": {
          "calcs": [
            "lastNotNull"
          ],
          "fields": "",
          "values": false
        },
        "text": {},
        "textMode": "auto"
      },
      "pluginVersion": "8.2.1",
      "targets": [
        {
          "exemplar": true,
          "expr": "cnp_pg_replication_is_replicating{namespace=~\"$namespace\",pod=~\"$cluster-.*\"}",
          "instant": true,
          "interval": "",
          "legendFormat": "{{pod}}",
          "refId": "A"
        }
      ],
      "title": "Participating in replication?",
      "type": "stat"
    },
    {
      "datasource": null,
      "fieldConfig": {
        "defaults": {
          "color": {
            "mode": "thresholds"
          },
          "mappings": [],
          "thresholds": {
            "mode": "absolute",
            "steps": [
              {
                "color": "green",
                "value": null
              },
              {
                "color": "#EAB839",
                "value": 75
              },
              {
                "color": "dark-red",
                "value": 90
              }
            ]
          }
        },
        "overrides": []
      },
      "gridPos": {
        "h": 7,
        "w": 4,
        "x": 8,
        "y": 1
      },
      "id": 58,
      "options": {
        "orientation": "auto",
        "reduceOptions": {
          "calcs": [
            "lastNotNull"
          ],
          "fields": "",
          "values": false
        },
        "showThresholdLabels": false,
        "showThresholdMarkers": false,
        "text": {}
      },
      "pluginVersion": "8.2.1",
      "targets": [
        {
          "exemplar": true,
          "expr": "sum by (pod) (cnp_backends_total{namespace=~\"$namespace\",pod=~\"$cluster-.*\"})",
          "instant": false,
          "interval": "",
          "legendFormat": "{{pod}}",
          "refId": "A"
        }
      ],
      "title": "Connections",
      "type": "gauge"
    },
    {
      "datasource": null,
      "description": "",
      "fieldConfig": {
        "defaults": {
          "color": {
            "mode": "thresholds"
          },
          "decimals": 0,
          "mappings": [],
          "max": 100,
          "noValue": "<1%",
          "thresholds": {
            "mode": "absolute",
            "steps": [
              {
                "color": "green",
                "value": null
              },
              {
                "color": "#EAB839",
                "value": 75
              },
              {
                "color": "red",
                "value": 90
              }
            ]
          },
          "unit": "percent"
        },
        "overrides": []
      },
      "gridPos": {
        "h": 7,
        "w": 6,
        "x": 12,
        "y": 1
      },
      "id": 32,
      "options": {
        "orientation": "auto",
        "reduceOptions": {
          "calcs": [
            "last"
          ],
          "fields": "",
          "values": false
        },
        "showThresholdLabels": false,
        "showThresholdMarkers": true,
        "text": {}
      },
      "pluginVersion": "8.2.1",
      "targets": [
        {
          "exemplar": true,
          "expr": "100 * sum by (pod) (cnp_backends_total{namespace=~\"$namespace\",pod=~\"$cluster-.*\"}) / sum by (pod) (cnp_pg_settings_setting{name=\"max_connections\",namespace=~\"$namespace\",pod=~\"$cluster-.*\"})",
          "instant": true,
          "interval": "",
          "legendFormat": "{{pod}}",
          "refId": "A"
        }
      ],
      "title": "Connections Used",
      "type": "gauge"
    },
    {
      "datasource": null,
      "fieldConfig": {
        "defaults": {
          "color": {
            "mode": "thresholds"
          },
          "mappings": [],
          "max": 2147483647,
          "min": 0,
          "thresholds": {
            "mode": "absolute",
            "steps": [
              {
                "color": "green",
                "value": null
              },
              {
                "color": "#EAB839",
                "value": 200000000
              },
              {
                "color": "red",
                "value": 1000000000
              }
            ]
          },
          "unit": "none"
        },
        "overrides": []
      },
      "gridPos": {
        "h": 7,
        "w": 6,
        "x": 18,
        "y": 1
      },
      "id": 8,
      "options": {
        "displayMode": "lcd",
        "orientation": "horizontal",
        "reduceOptions": {
          "calcs": [
            "lastNotNull"
          ],
          "fields": "",
          "values": false
        },
        "showUnfilled": true,
        "text": {}
      },
      "pluginVersion": "8.2.1",
      "targets": [
        {
          "exemplar": true,
          "expr": "max by (pod) (cnp_pg_database_xid_age{namespace=~\"$namespace\",pod=~\"$cluster-.*\"})",
          "instant": true,
          "interval": "",
          "legendFormat": "{{pod}}",
          "refId": "A"
        }
      ],
      "title": "Wraparound",
      "type": "bargauge"
    },
    {
      "collapsed": false,
      "datasource": null,
      "gridPos": {
        "h": 1,
        "w": 24,
        "x": 0,
        "y": 8
      },
      "id": 41,
      "panels": [],
      "title": "Configuration",
      "type": "row"
    },
    {
      "datasource": null,
      "description": "",
      "fieldConfig": {
        "defaults": {
          "color": {
            "mode": "thresholds"
          },
          "mappings": [],
          "thresholds": {
            "mode": "absolute",
            "steps": [
              {
                "color": "dark-blue",
                "value": null
              }
            ]
          },
          "unit": "string"
        },
        "overrides": []
      },
      "gridPos": {
        "h": 7,
        "w": 3,
        "x": 0,
        "y": 9
      },
      "id": 42,
      "options": {
        "colorMode": "background",
        "graphMode": "none",
        "justifyMode": "auto",
        "orientation": "horizontal",
        "reduceOptions": {
          "calcs": [
            "lastNotNull"
          ],
          "fields": "",
          "values": false
        },
        "text": {},
        "textMode": "auto"
      },
      "pluginVersion": "8.2.1",
      "targets": [
        {
          "exemplar": false,
          "expr": "max(cnp_collector_postgres_version{namespace=~\"$namespace\",pod=~\"$cluster-.*\"})",
          "format": "time_series",
          "hide": false,
          "instant": true,
          "interval": "",
          "intervalFactor": 1,
          "legendFormat": "{{pod}}",
          "refId": "A"
        }
      ],
      "title": "Server Version",
      "transformations": [],
      "type": "stat"
    },
    {
      "datasource": null,
      "fieldConfig": {
        "defaults": {
          "color": {
            "mode": "thresholds"
          },
          "mappings": [],
          "thresholds": {
            "mode": "absolute",
            "steps": [
              {
                "color": "dark-purple",
                "value": null
              }
            ]
          }
        },
        "overrides": []
      },
      "gridPos": {
        "h": 7,
        "w": 3,
        "x": 3,
        "y": 9
      },
      "id": 30,
      "options": {
        "colorMode": "background",
        "graphMode": "none",
        "justifyMode": "auto",
        "orientation": "horizontal",
        "reduceOptions": {
          "calcs": [
            "lastNotNull"
          ],
          "fields": "",
          "values": false
        },
        "text": {},
        "textMode": "auto"
      },
      "pluginVersion": "8.2.1",
      "targets": [
        {
          "exemplar": true,
          "expr": "cnp_pg_settings_setting{name=\"max_connections\",namespace=~\"$namespace\",pod=~\"$cluster-.*\"}",
          "instant": true,
          "interval": "",
          "legendFormat": "{{pod}}",
          "refId": "A"
        }
      ],
      "title": "Max Connections",
      "type": "stat"
    },
    {
      "datasource": null,
      "description": "",
      "fieldConfig": {
        "defaults": {
          "color": {
            "mode": "thresholds"
          },
          "mappings": [],
          "thresholds": {
            "mode": "absolute",
            "steps": [
              {
                "color": "dark-purple",
                "value": null
              }
            ]
          },
          "unit": "bytes"
        },
        "overrides": []
      },
      "gridPos": {
        "h": 7,
        "w": 3,
        "x": 6,
        "y": 9
      },
      "id": 24,
      "options": {
        "colorMode": "background",
        "graphMode": "none",
        "justifyMode": "auto",
        "orientation": "horizontal",
        "reduceOptions": {
          "calcs": [
            "lastNotNull"
          ],
          "fields": "",
          "values": false
        },
        "text": {},
        "textMode": "auto"
      },
      "pluginVersion": "8.2.1",
      "targets": [
        {
          "exemplar": true,
          "expr": "max by (pod) (cnp_pg_settings_setting{name=\"shared_buffers\",namespace=~\"$namespace\",pod=~\"$cluster-.*\"}) * max by (pod) (cnp_pg_settings_setting{name=\"block_size\",namespace=~\"$namespace\",pod=~\"$cluster-.*\"})",
          "instant": true,
          "interval": "",
          "legendFormat": "{{pod}}",
          "refId": "A"
        }
      ],
      "title": "Shared Buffers",
      "type": "stat"
    },
    {
      "datasource": null,
      "description": "",
      "fieldConfig": {
        "defaults": {
          "color": {
            "mode": "thresholds"
          },
          "mappings": [],
          "thresholds": {
            "mode": "absolute",
            "steps": [
              {
                "color": "dark-purple",
                "value": null
              }
            ]
          },
          "unit": "bytes"
        },
        "overrides": []
      },
      "gridPos": {
        "h": 7,
        "w": 3,
        "x": 9,
        "y": 9
      },
      "id": 57,
      "options": {
        "colorMode": "background",
        "graphMode": "none",
        "justifyMode": "auto",
        "orientation": "horizontal",
        "reduceOptions": {
          "calcs": [
            "lastNotNull"
          ],
          "fields": "",
          "values": false
        },
        "text": {},
        "textMode": "auto"
      },
      "pluginVersion": "8.2.1",
      "targets": [
        {
          "exemplar": true,
          "expr": "cnp_pg_settings_setting{name=\"effective_cache_size\",namespace=~\"$namespace\",pod=~\"$cluster-.*\"}",
          "instant": true,
          "interval": "",
          "legendFormat": "{{pod}}",
          "refId": "A"
        }
      ],
      "title": "Effective Cache Size",
      "type": "stat"
    },
    {
      "datasource": null,
      "description": "",
      "fieldConfig": {
        "defaults": {
          "color": {
            "mode": "thresholds"
          },
          "mappings": [],
          "thresholds": {
            "mode": "absolute",
            "steps": [
              {
                "color": "dark-purple",
                "value": null
              }
            ]
          },
          "unit": "mbytes"
        },
        "overrides": []
      },
      "gridPos": {
        "h": 7,
        "w": 3,
        "x": 12,
        "y": 9
      },
      "id": 26,
      "options": {
        "colorMode": "background",
        "graphMode": "none",
        "justifyMode": "auto",
        "orientation": "horizontal",
        "reduceOptions": {
          "calcs": [
            "lastNotNull"
          ],
          "fields": "",
          "values": false
        },
        "text": {},
        "textMode": "auto"
      },
      "pluginVersion": "8.2.1",
      "targets": [
        {
          "exemplar": true,
          "expr": "cnp_pg_settings_setting{name=\"work_mem\",namespace=~\"$namespace\",pod=~\"$cluster-.*\"}",
          "instant": true,
          "interval": "",
          "legendFormat": "{{pod}}",
          "refId": "A"
        }
      ],
      "title": "Work Mem",
      "type": "stat"
    },
    {
      "datasource": null,
      "fieldConfig": {
        "defaults": {
          "color": {
            "mode": "thresholds"
          },
          "mappings": [],
          "thresholds": {
            "mode": "absolute",
            "steps": [
              {
                "color": "dark-purple",
                "value": null
              }
            ]
          },
          "unit": "bytes"
        },
        "overrides": []
      },
      "gridPos": {
        "h": 7,
        "w": 3,
        "x": 15,
        "y": 9
      },
      "id": 47,
      "options": {
        "colorMode": "background",
        "graphMode": "none",
        "justifyMode": "auto",
        "orientation": "horizontal",
        "reduceOptions": {
          "calcs": [
            "lastNotNull"
          ],
          "fields": "",
          "values": false
        },
        "text": {},
        "textMode": "auto"
      },
      "pluginVersion": "8.2.1",
      "targets": [
        {
          "exemplar": true,
          "expr": "cnp_pg_settings_setting{name=\"maintenance_work_mem\",namespace=~\"$namespace\",pod=~\"$cluster-.*\"}",
          "instant": true,
          "interval": "",
          "legendFormat": "{{pod}}",
          "refId": "A"
        }
      ],
      "title": "Maintenance Work Mem",
      "type": "stat"
    },
    {
      "datasource": null,
      "fieldConfig": {
        "defaults": {
          "color": {
            "mode": "thresholds"
          },
          "mappings": [],
          "thresholds": {
            "mode": "absolute",
            "steps": [
              {
                "color": "dark-purple",
                "value": null
              }
            ]
          },
          "unit": "none"
        },
        "overrides": []
      },
      "gridPos": {
        "h": 7,
        "w": 3,
        "x": 18,
        "y": 9
      },
      "id": 48,
      "options": {
        "colorMode": "background",
        "graphMode": "none",
        "justifyMode": "auto",
        "orientation": "horizontal",
        "reduceOptions": {
          "calcs": [
            "lastNotNull"
          ],
          "fields": "",
          "values": false
        },
        "text": {},
        "textMode": "auto"
      },
      "pluginVersion": "8.2.1",
      "targets": [
        {
          "exemplar": true,
          "expr": "cnp_pg_settings_setting{name=\"random_page_cost\",namespace=~\"$namespace\",pod=~\"$cluster-.*\"}",
          "instant": true,
          "interval": "",
          "legendFormat": "{{pod}}",
          "refId": "A"
        }
      ],
      "title": "Random Page Cost",
      "type": "stat"
    },
    {
      "datasource": null,
      "fieldConfig": {
        "defaults": {
          "color": {
            "mode": "thresholds"
          },
          "mappings": [],
          "thresholds": {
            "mode": "absolute",
            "steps": [
              {
                "color": "dark-purple",
                "value": null
              }
            ]
          },
          "unit": "none"
        },
        "overrides": []
      },
      "gridPos": {
        "h": 7,
        "w": 3,
        "x": 21,
        "y": 9
      },
      "id": 56,
      "options": {
        "colorMode": "background",
        "graphMode": "none",
        "justifyMode": "auto",
        "orientation": "horizontal",
        "reduceOptions": {
          "calcs": [
            "lastNotNull"
          ],
          "fields": "",
          "values": false
        },
        "text": {},
        "textMode": "auto"
      },
      "pluginVersion": "8.2.1",
      "targets": [
        {
          "exemplar": true,
          "expr": "cnp_pg_settings_setting{name=\"seq_page_cost\",namespace=~\"$namespace\",pod=~\"$cluster-.*\"}",
          "instant": true,
          "interval": "",
          "legendFormat": "{{pod}}",
          "refId": "A"
        }
      ],
      "title": "Sequential Page Cost",
      "type": "stat"
    },
    {
      "collapsed": false,
      "datasource": null,
      "gridPos": {
        "h": 1,
        "w": 24,
        "x": 0,
        "y": 16
      },
      "id": 10,
      "panels": [],
      "title": "Operational Stats",
      "type": "row"
    },
    {
      "datasource": null,
      "description": "",
      "fieldConfig": {
        "defaults": {
          "color": {
            "mode": "palette-classic"
          },
          "custom": {
            "axisLabel": "",
            "axisPlacement": "auto",
            "barAlignment": 0,
            "drawStyle": "line",
            "fillOpacity": 10,
            "gradientMode": "opacity",
            "hideFrom": {
              "legend": false,
              "tooltip": false,
              "viz": false
            },
            "lineInterpolation": "linear",
            "lineWidth": 1,
            "pointSize": 5,
            "scaleDistribution": {
              "type": "linear"
            },
            "showPoints": "never",
            "spanNulls": true,
            "stacking": {
              "group": "A",
              "mode": "none"
            },
            "thresholdsStyle": {
              "mode": "off"
            }
          },
          "mappings": [],
          "thresholds": {
            "mode": "absolute",
            "steps": [
              {
                "color": "green",
                "value": null
              }
            ]
          }
        },
        "overrides": []
      },
      "gridPos": {
        "h": 8,
        "w": 24,
        "x": 0,
        "y": 17
      },
      "id": 39,
      "options": {
        "legend": {
          "calcs": [],
          "displayMode": "list",
          "placement": "bottom"
        },
        "tooltip": {
          "mode": "single"
        }
      },
      "targets": [
        {
          "exemplar": true,
          "expr": "sum(cnp_backends_total{namespace=~\"$namespace\",pod=~\"$cluster-.*\"}) by (pod)",
          "hide": false,
          "interval": "",
          "legendFormat": "total ({{pod}})",
          "refId": "B"
        },
        {
          "exemplar": true,
          "expr": "sum(cnp_backends_total{namespace=~\"$namespace\",pod=~\"$cluster-.*\"}) by (state, pod)",
          "interval": "",
          "legendFormat": "{{state}} ({{pod}})",
          "refId": "A"
        }
      ],
      "title": "Session States",
      "type": "timeseries"
    },
    {
      "datasource": null,
      "fieldConfig": {
        "defaults": {
          "color": {
            "mode": "palette-classic"
          },
          "custom": {
            "axisLabel": "",
            "axisPlacement": "auto",
            "barAlignment": 0,
            "drawStyle": "line",
            "fillOpacity": 10,
            "gradientMode": "opacity",
            "hideFrom": {
              "legend": false,
              "tooltip": false,
              "viz": false
            },
            "lineInterpolation": "linear",
            "lineWidth": 1,
            "pointSize": 5,
            "scaleDistribution": {
              "type": "linear"
            },
            "showPoints": "never",
            "spanNulls": true,
            "stacking": {
              "group": "A",
              "mode": "none"
            },
            "thresholdsStyle": {
              "mode": "off"
            }
          },
          "mappings": [],
          "thresholds": {
            "mode": "absolute",
            "steps": [
              {
                "color": "green",
                "value": null
              },
              {
                "color": "red",
                "value": 80
              }
            ]
          }
        },
        "overrides": []
      },
      "gridPos": {
        "h": 8,
        "w": 12,
        "x": 0,
        "y": 25
      },
      "id": 50,
      "options": {
        "legend": {
          "calcs": [],
          "displayMode": "list",
          "placement": "bottom"
        },
        "tooltip": {
          "mode": "single"
        }
      },
      "targets": [
        {
          "exemplar": true,
          "expr": "sum(rate(cnp_pg_stat_database_xact_commit{namespace=~\"$namespace\",pod=~\"$cluster-.*\"}[5m])) by (pod)",
          "interval": "",
          "legendFormat": "committed ({{pod}})",
          "refId": "A"
        },
        {
          "exemplar": true,
          "expr": "sum(rate(cnp_pg_stat_database_xact_rollback{namespace=~\"$namespace\",pod=~\"$cluster-.*\"}[5m])) by (pod)",
          "hide": false,
          "interval": "",
          "legendFormat": "rolled back ({{pod}})",
          "refId": "B"
        }
      ],
      "title": "Transactions [5m]",
      "type": "timeseries"
    },
    {
      "datasource": null,
      "description": "",
      "fieldConfig": {
        "defaults": {
          "color": {
            "mode": "palette-classic"
          },
          "custom": {
            "axisLabel": "",
            "axisPlacement": "auto",
            "barAlignment": 0,
            "drawStyle": "line",
            "fillOpacity": 10,
            "gradientMode": "none",
            "hideFrom": {
              "legend": false,
              "tooltip": false,
              "viz": false
            },
            "lineInterpolation": "linear",
            "lineWidth": 1,
            "pointSize": 5,
            "scaleDistribution": {
              "type": "linear"
            },
            "showPoints": "never",
            "spanNulls": true,
            "stacking": {
              "group": "A",
              "mode": "none"
            },
            "thresholdsStyle": {
              "mode": "off"
            }
          },
          "mappings": [],
          "thresholds": {
            "mode": "absolute",
            "steps": [
              {
                "color": "green",
                "value": null
              },
              {
                "color": "red",
                "value": 80
              }
            ]
          },
          "unit": "s"
        },
        "overrides": []
      },
      "gridPos": {
        "h": 8,
        "w": 12,
        "x": 12,
        "y": 25
      },
      "id": 4,
      "options": {
        "legend": {
          "calcs": [],
          "displayMode": "list",
          "placement": "bottom"
        },
        "tooltip": {
          "mode": "single"
        }
      },
      "targets": [
        {
          "exemplar": true,
          "expr": "max by (pod) (cnp_backends_max_tx_duration_seconds{namespace=~\"$namespace\",pod=~\"$cluster-.*\"})",
          "interval": "",
          "legendFormat": "{{pod}}",
          "refId": "A"
        }
      ],
      "title": "Longest Transaction",
      "type": "timeseries"
    },
    {
      "datasource": null,
      "description": "",
      "fieldConfig": {
        "defaults": {
          "color": {
            "mode": "palette-classic"
          },
          "custom": {
            "axisLabel": "",
            "axisPlacement": "auto",
            "barAlignment": 0,
            "drawStyle": "line",
            "fillOpacity": 10,
            "gradientMode": "none",
            "hideFrom": {
              "legend": false,
              "tooltip": false,
              "viz": false
            },
            "lineInterpolation": "linear",
            "lineWidth": 1,
            "pointSize": 5,
            "scaleDistribution": {
              "type": "linear"
            },
            "showPoints": "never",
            "spanNulls": true,
            "stacking": {
              "group": "A",
              "mode": "none"
            },
            "thresholdsStyle": {
              "mode": "off"
            }
          },
          "mappings": [],
          "thresholds": {
            "mode": "absolute",
            "steps": [
              {
                "color": "green",
                "value": null
              },
              {
                "color": "red",
                "value": 80
              }
            ]
          }
        },
        "overrides": []
      },
      "gridPos": {
        "h": 8,
        "w": 12,
        "x": 0,
        "y": 33
      },
      "id": 55,
      "options": {
        "legend": {
          "calcs": [],
          "displayMode": "list",
          "placement": "bottom"
        },
        "tooltip": {
          "mode": "single"
        }
      },
      "targets": [
        {
          "exemplar": true,
          "expr": "rate(cnp_pg_stat_database_deadlocks{datname=\"\",namespace=~\"$namespace\",pod=~\"$cluster-.*\"}[5m])",
          "hide": false,
          "instant": false,
          "interval": "",
          "legendFormat": "count ({{pod}})",
          "refId": "B"
        }
      ],
      "title": "Deadlocks [5m]",
      "type": "timeseries"
    },
    {
      "datasource": null,
      "description": "",
      "fieldConfig": {
        "defaults": {
          "color": {
            "mode": "palette-classic"
          },
          "custom": {
            "axisLabel": "",
            "axisPlacement": "auto",
            "barAlignment": 0,
            "drawStyle": "line",
            "fillOpacity": 10,
            "gradientMode": "none",
            "hideFrom": {
              "legend": false,
              "tooltip": false,
              "viz": false
            },
            "lineInterpolation": "linear",
            "lineWidth": 1,
            "pointSize": 5,
            "scaleDistribution": {
              "type": "linear"
            },
            "showPoints": "never",
            "spanNulls": true,
            "stacking": {
              "group": "A",
              "mode": "none"
            },
            "thresholdsStyle": {
              "mode": "off"
            }
          },
          "mappings": [],
          "thresholds": {
            "mode": "absolute",
            "steps": [
              {
                "color": "green",
                "value": null
              },
              {
                "color": "red",
                "value": 80
              }
            ]
          }
        },
        "overrides": []
      },
      "gridPos": {
        "h": 8,
        "w": 12,
        "x": 12,
        "y": 33
      },
      "id": 54,
      "options": {
        "legend": {
          "calcs": [],
          "displayMode": "list",
          "placement": "bottom"
        },
        "tooltip": {
          "mode": "single"
        }
      },
      "targets": [
        {
          "exemplar": true,
          "expr": "cnp_backends_waiting_total{namespace=~\"$namespace\",pod=~\"$cluster-.*\"}",
          "interval": "",
          "legendFormat": "{{pod}}",
          "refId": "A"
        }
      ],
      "title": "Blocked Queries",
      "type": "timeseries"
    },
    {
      "collapsed": false,
      "datasource": null,
      "gridPos": {
        "h": 1,
        "w": 24,
        "x": 0,
        "y": 41
      },
      "id": 35,
      "panels": [],
      "title": "Storage & I/O",
      "type": "row"
    },
    {
      "datasource": null,
      "fieldConfig": {
        "defaults": {
          "color": {
            "mode": "palette-classic"
          },
          "custom": {
            "axisLabel": "",
            "axisPlacement": "auto",
            "barAlignment": 0,
            "drawStyle": "line",
            "fillOpacity": 10,
            "gradientMode": "none",
            "hideFrom": {
              "legend": false,
              "tooltip": false,
              "viz": false
            },
            "lineInterpolation": "linear",
            "lineWidth": 1,
            "pointSize": 5,
            "scaleDistribution": {
              "type": "linear"
            },
            "showPoints": "never",
            "spanNulls": true,
            "stacking": {
              "group": "A",
              "mode": "none"
            },
            "thresholdsStyle": {
              "mode": "off"
            }
          },
          "mappings": [],
          "thresholds": {
            "mode": "absolute",
            "steps": [
              {
                "color": "green",
                "value": null
              },
              {
                "color": "red",
                "value": 80
              }
            ]
          }
        },
        "overrides": []
      },
      "gridPos": {
        "h": 8,
        "w": 12,
        "x": 0,
        "y": 42
      },
      "id": 44,
      "options": {
        "legend": {
          "calcs": [],
          "displayMode": "list",
          "placement": "bottom"
        },
        "tooltip": {
          "mode": "single"
        }
      },
      "targets": [
        {
          "exemplar": true,
          "expr": "rate(cnp_pg_stat_database_tup_deleted{datname=\"\",namespace=~\"$namespace\",pod=~\"$cluster-.*\"}[5m])",
          "interval": "",
          "legendFormat": "deleted ({{pod}})",
          "refId": "A"
        },
        {
          "exemplar": true,
          "expr": "rate(cnp_pg_stat_database_tup_inserted{datname=\"\",namespace=~\"$namespace\",pod=~\"$cluster-.*\"}[5m])",
          "hide": false,
          "interval": "",
          "legendFormat": "inserted ({{pod}})",
          "refId": "B"
        },
        {
          "exemplar": true,
          "expr": "rate(cnp_pg_stat_database_tup_fetched{datname=\"\",namespace=~\"$namespace\",pod=~\"$cluster-.*\"}[5m])",
          "hide": false,
          "interval": "",
          "legendFormat": "fetched ({{pod}})",
          "refId": "C"
        },
        {
          "exemplar": true,
          "expr": "rate(cnp_pg_stat_database_tup_returned{datname=\"\",namespace=~\"$namespace\",pod=~\"$cluster-.*\"}[5m])",
          "hide": false,
          "interval": "",
          "legendFormat": "returned ({{pod}})",
          "refId": "D"
        },
        {
          "exemplar": true,
          "expr": "rate(cnp_pg_stat_database_tup_updated{datname=\"\",namespace=~\"$namespace\",pod=~\"$cluster-.*\"}[5m])",
          "hide": false,
          "interval": "",
          "legendFormat": "updated ({{pod}})",
          "refId": "E"
        }
      ],
      "title": "Tuple I/O [5m]",
      "type": "timeseries"
    },
    {
      "datasource": null,
      "fieldConfig": {
        "defaults": {
          "color": {
            "mode": "palette-classic"
          },
          "custom": {
            "axisLabel": "",
            "axisPlacement": "auto",
            "barAlignment": 0,
            "drawStyle": "line",
            "fillOpacity": 10,
            "gradientMode": "none",
            "hideFrom": {
              "legend": false,
              "tooltip": false,
              "viz": false
            },
            "lineInterpolation": "linear",
            "lineWidth": 1,
            "pointSize": 5,
            "scaleDistribution": {
              "type": "linear"
            },
            "showPoints": "never",
            "spanNulls": true,
            "stacking": {
              "group": "A",
              "mode": "none"
            },
            "thresholdsStyle": {
              "mode": "off"
            }
          },
          "mappings": [],
          "thresholds": {
            "mode": "absolute",
            "steps": [
              {
                "color": "green",
                "value": null
              },
              {
                "color": "red",
                "value": 80
              }
            ]
          }
        },
        "overrides": []
      },
      "gridPos": {
        "h": 8,
        "w": 12,
        "x": 12,
        "y": 42
      },
      "id": 46,
      "options": {
        "legend": {
          "calcs": [],
          "displayMode": "list",
          "placement": "bottom"
        },
        "tooltip": {
          "mode": "single"
        }
      },
      "targets": [
        {
          "exemplar": true,
          "expr": "rate(cnp_pg_stat_database_blks_hit{datname=\"\"}[5m])",
          "interval": "",
          "legendFormat": "hit ({{pod}})",
          "refId": "A"
        },
        {
          "exemplar": true,
          "expr": "rate(cnp_pg_stat_database_blks_read{datname=\"\"}[5m])",
          "hide": false,
          "interval": "",
          "legendFormat": "read ({{pod}})",
          "refId": "B"
        }
      ],
      "title": "Block I/O [5m]",
      "type": "timeseries"
    },
    {
      "datasource": null,
      "fieldConfig": {
        "defaults": {
          "color": {
            "mode": "palette-classic"
          },
          "custom": {
            "axisLabel": "",
            "axisPlacement": "auto",
            "barAlignment": 0,
            "drawStyle": "line",
            "fillOpacity": 10,
            "gradientMode": "none",
            "hideFrom": {
              "legend": false,
              "tooltip": false,
              "viz": false
            },
            "lineInterpolation": "linear",
            "lineWidth": 1,
            "pointSize": 5,
            "scaleDistribution": {
              "type": "linear"
            },
            "showPoints": "never",
            "spanNulls": true,
            "stacking": {
              "group": "A",
              "mode": "none"
            },
            "thresholdsStyle": {
              "mode": "off"
            }
          },
          "mappings": [],
          "thresholds": {
            "mode": "absolute",
            "steps": [
              {
                "color": "green",
                "value": null
              }
            ]
          },
          "unit": "decbytes"
        },
        "overrides": []
      },
      "gridPos": {
        "h": 8,
        "w": 12,
        "x": 0,
        "y": 50
      },
      "id": 22,
      "options": {
        "legend": {
          "calcs": [],
          "displayMode": "list",
          "placement": "bottom"
        },
        "tooltip": {
          "mode": "single"
        }
      },
      "pluginVersion": "8.0.5",
      "targets": [
        {
          "exemplar": true,
          "expr": "cnp_pg_database_size_bytes{datname!~\"template.*\",datname!=\"postgres\",namespace=~\"$namespace\",pod=~\"$cluster-.*\"}",
          "interval": "",
          "legendFormat": "{{datname}} ({{pod}})",
          "refId": "A"
        }
      ],
      "title": "Database Size",
      "type": "timeseries"
    },
    {
      "datasource": null,
      "fieldConfig": {
        "defaults": {
          "color": {
            "mode": "palette-classic"
          },
          "custom": {
            "axisLabel": "",
            "axisPlacement": "auto",
            "barAlignment": 0,
            "drawStyle": "line",
            "fillOpacity": 10,
            "gradientMode": "none",
            "hideFrom": {
              "legend": false,
              "tooltip": false,
              "viz": false
            },
            "lineInterpolation": "linear",
            "lineWidth": 1,
            "pointSize": 5,
            "scaleDistribution": {
              "type": "linear"
            },
            "showPoints": "never",
            "spanNulls": true,
            "stacking": {
              "group": "A",
              "mode": "none"
            },
            "thresholdsStyle": {
              "mode": "off"
            }
          },
          "mappings": [],
          "thresholds": {
            "mode": "absolute",
            "steps": [
              {
                "color": "green",
                "value": null
              },
              {
                "color": "red",
                "value": 80
              }
            ]
          },
          "unit": "decbytes"
        },
        "overrides": []
      },
      "gridPos": {
        "h": 8,
        "w": 12,
        "x": 12,
        "y": 50
      },
      "id": 2,
      "options": {
        "legend": {
          "calcs": [],
          "displayMode": "list",
          "placement": "bottom"
        },
        "tooltip": {
          "mode": "single"
        }
      },
      "targets": [
        {
          "exemplar": true,
          "expr": "rate(cnp_pg_stat_database_temp_bytes{datname=\"\",namespace=~\"$namespace\",pod=~\"$cluster-.*\"}[5m])",
          "instant": false,
          "interval": "",
          "legendFormat": "{{pod}}",
          "refId": "A"
        }
      ],
      "title": "Temp Bytes [5m]",
      "type": "timeseries"
    },
    {
      "collapsed": false,
      "datasource": null,
      "gridPos": {
        "h": 1,
        "w": 24,
        "x": 0,
        "y": 58
      },
      "id": 37,
      "panels": [],
      "title": "Write Ahead Log",
      "type": "row"
    },
    {
      "datasource": null,
      "fieldConfig": {
        "defaults": {
          "color": {
            "mode": "palette-classic"
          },
          "custom": {
            "axisLabel": "",
            "axisPlacement": "auto",
            "barAlignment": 0,
            "drawStyle": "line",
            "fillOpacity": 10,
            "gradientMode": "none",
            "hideFrom": {
              "legend": false,
              "tooltip": false,
              "viz": false
            },
            "lineInterpolation": "linear",
            "lineWidth": 1,
            "pointSize": 5,
            "scaleDistribution": {
              "type": "linear"
            },
            "showPoints": "never",
            "spanNulls": true,
            "stacking": {
              "group": "A",
              "mode": "none"
            },
            "thresholdsStyle": {
              "mode": "off"
            }
          },
          "mappings": [],
          "thresholds": {
            "mode": "absolute",
            "steps": [
              {
                "color": "green",
                "value": null
              },
              {
                "color": "red",
                "value": 80
              }
            ]
          }
        },
        "overrides": []
      },
      "gridPos": {
        "h": 8,
        "w": 8,
        "x": 0,
        "y": 59
      },
      "id": 6,
      "options": {
        "legend": {
          "calcs": [],
          "displayMode": "list",
          "placement": "bottom"
        },
        "tooltip": {
          "mode": "single"
        }
      },
      "targets": [
        {
          "exemplar": true,
          "expr": "cnp_collector_pg_wal_archive_status{value=\"ready\",namespace=~\"$namespace\",pod=~\"$cluster-.*\"}",
          "interval": "",
          "legendFormat": "ready ({{pod}})",
          "refId": "A"
        },
        {
          "exemplar": true,
          "expr": "cnp_collector_pg_wal_archive_status{value=\"done\",namespace=~\"$namespace\",pod=~\"$cluster-.*\"}",
          "hide": false,
          "interval": "",
          "legendFormat": "done ({{pod}})",
          "refId": "B"
        }
      ],
      "title": "WAL Segment Archive Status",
      "type": "timeseries"
    },
    {
      "datasource": null,
      "fieldConfig": {
        "defaults": {
          "color": {
            "mode": "palette-classic"
          },
          "custom": {
            "axisLabel": "",
            "axisPlacement": "auto",
            "barAlignment": 0,
            "drawStyle": "line",
            "fillOpacity": 10,
            "gradientMode": "none",
            "hideFrom": {
              "legend": false,
              "tooltip": false,
              "viz": false
            },
            "lineInterpolation": "linear",
            "lineWidth": 1,
            "pointSize": 5,
            "scaleDistribution": {
              "type": "linear"
            },
            "showPoints": "never",
            "spanNulls": true,
            "stacking": {
              "group": "A",
              "mode": "none"
            },
            "thresholdsStyle": {
              "mode": "off"
            }
          },
          "mappings": [],
          "thresholds": {
            "mode": "absolute",
            "steps": [
              {
                "color": "green",
                "value": null
              },
              {
                "color": "red",
                "value": 80
              }
            ]
          }
        },
        "overrides": []
      },
      "gridPos": {
        "h": 8,
        "w": 8,
        "x": 8,
        "y": 59
      },
      "id": 52,
      "options": {
        "legend": {
          "calcs": [],
          "displayMode": "list",
          "placement": "bottom"
        },
        "tooltip": {
          "mode": "single"
        }
      },
      "targets": [
        {
          "exemplar": true,
          "expr": "rate(cnp_pg_stat_archiver_archived_count{namespace=~\"$namespace\",pod=~\"$cluster-.*\"}[5m])",
          "interval": "",
          "legendFormat": "archived ({{pod}})",
          "refId": "A"
        },
        {
          "exemplar": true,
          "expr": "rate(cnp_pg_stat_archiver_failed_count{namespace=~\"$namespace\",pod=~\"$cluster-.*\"}[5m])",
          "hide": false,
          "interval": "",
          "legendFormat": "failed ({{pod}})",
          "refId": "B"
        }
      ],
      "title": "Archiver Status [5m]",
      "type": "timeseries"
    },
    {
      "datasource": null,
      "description": "",
      "fieldConfig": {
        "defaults": {
          "color": {
            "mode": "palette-classic"
          },
          "custom": {
            "axisLabel": "",
            "axisPlacement": "auto",
            "barAlignment": 0,
            "drawStyle": "line",
            "fillOpacity": 10,
            "gradientMode": "none",
            "hideFrom": {
              "legend": false,
              "tooltip": false,
              "viz": false
            },
            "lineInterpolation": "linear",
            "lineWidth": 1,
            "pointSize": 5,
            "scaleDistribution": {
              "type": "linear"
            },
            "showPoints": "never",
            "spanNulls": true,
            "stacking": {
              "group": "A",
              "mode": "none"
            },
            "thresholdsStyle": {
              "mode": "off"
            }
          },
          "mappings": [],
          "thresholds": {
            "mode": "absolute",
            "steps": [
              {
                "color": "green",
                "value": null
              },
              {
                "color": "red",
                "value": 80
              }
            ]
          },
          "unit": "s"
        },
        "overrides": []
      },
      "gridPos": {
        "h": 8,
        "w": 8,
        "x": 16,
        "y": 59
      },
      "id": 53,
      "options": {
        "legend": {
          "calcs": [],
          "displayMode": "list",
          "placement": "bottom"
        },
        "tooltip": {
          "mode": "single"
        }
      },
      "targets": [
        {
          "exemplar": true,
          "expr": "cnp_pg_stat_archiver_seconds_since_last_archival{namespace=~\"$namespace\",pod=~\"$cluster-.*\"}",
          "interval": "",
          "legendFormat": "age ({{pod}})",
          "refId": "A"
        }
      ],
      "title": "Last Archive Age",
      "type": "timeseries"
    },
    {
      "collapsed": false,
      "datasource": null,
      "gridPos": {
        "h": 1,
        "w": 24,
        "x": 0,
        "y": 67
      },
      "id": 18,
      "panels": [],
      "title": "Replication",
      "type": "row"
    },
    {
      "datasource": null,
      "fieldConfig": {
        "defaults": {
          "color": {
            "mode": "palette-classic"
          },
          "custom": {
            "axisLabel": "",
            "axisPlacement": "auto",
            "barAlignment": 0,
            "drawStyle": "line",
            "fillOpacity": 10,
            "gradientMode": "none",
            "hideFrom": {
              "legend": false,
              "tooltip": false,
              "viz": false
            },
            "lineInterpolation": "linear",
            "lineWidth": 1,
            "pointSize": 5,
            "scaleDistribution": {
              "type": "linear"
            },
            "showPoints": "never",
            "spanNulls": true,
            "stacking": {
              "group": "A",
              "mode": "none"
            },
            "thresholdsStyle": {
              "mode": "line"
            }
          },
          "mappings": [],
          "thresholds": {
            "mode": "absolute",
            "steps": [
              {
                "color": "green",
                "value": null
              },
              {
                "color": "#EAB839",
                "value": 600
              },
              {
                "color": "dark-red",
                "value": 3600
              }
            ]
          },
          "unit": "s"
        },
        "overrides": []
      },
      "gridPos": {
        "h": 8,
        "w": 6,
        "x": 0,
        "y": 68
      },
      "id": 16,
      "options": {
        "legend": {
          "calcs": [],
          "displayMode": "list",
          "placement": "bottom"
        },
        "tooltip": {
          "mode": "single"
        }
      },
      "targets": [
        {
          "exemplar": true,
          "expr": "cnp_pg_replication_lag{namespace=~\"$namespace\",pod=~\"$cluster-.*\"}",
          "interval": "",
          "legendFormat": "{{pod}}",
          "refId": "A"
        }
      ],
      "title": "Replication Lag",
      "type": "timeseries"
    },
    {
      "datasource": null,
      "fieldConfig": {
        "defaults": {
          "color": {
            "mode": "palette-classic"
          },
          "custom": {
            "axisLabel": "",
            "axisPlacement": "auto",
            "barAlignment": 0,
            "drawStyle": "line",
            "fillOpacity": 10,
            "gradientMode": "none",
            "hideFrom": {
              "legend": false,
              "tooltip": false,
              "viz": false
            },
            "lineInterpolation": "linear",
            "lineWidth": 1,
            "pointSize": 5,
            "scaleDistribution": {
              "type": "linear"
            },
            "showPoints": "never",
            "spanNulls": true,
            "stacking": {
              "group": "A",
              "mode": "none"
            },
            "thresholdsStyle": {
              "mode": "off"
            }
          },
          "mappings": [],
          "thresholds": {
            "mode": "absolute",
            "steps": [
              {
                "color": "green",
                "value": null
              },
              {
                "color": "red",
                "value": 80
              }
            ]
          },
          "unit": "s"
        },
        "overrides": []
      },
      "gridPos": {
        "h": 8,
        "w": 6,
        "x": 6,
        "y": 68
      },
      "id": 14,
      "options": {
        "legend": {
          "calcs": [],
          "displayMode": "list",
          "placement": "bottom"
        },
        "tooltip": {
          "mode": "single"
        }
      },
      "targets": [
        {
          "exemplar": true,
          "expr": "cnp_pg_stat_replication_write_lag_seconds{namespace=~\"$namespace\",pod=~\"$cluster-.*\"}",
          "instant": false,
          "interval": "",
          "legendFormat": "{{application_name}}",
          "refId": "A"
        }
      ],
      "title": "Write Lag",
      "type": "timeseries"
    },
    {
      "datasource": null,
      "fieldConfig": {
        "defaults": {
          "color": {
            "mode": "palette-classic"
          },
          "custom": {
            "axisLabel": "",
            "axisPlacement": "auto",
            "barAlignment": 0,
            "drawStyle": "line",
            "fillOpacity": 10,
            "gradientMode": "none",
            "hideFrom": {
              "legend": false,
              "tooltip": false,
              "viz": false
            },
            "lineInterpolation": "linear",
            "lineWidth": 1,
            "pointSize": 5,
            "scaleDistribution": {
              "type": "linear"
            },
            "showPoints": "never",
            "spanNulls": true,
            "stacking": {
              "group": "A",
              "mode": "none"
            },
            "thresholdsStyle": {
              "mode": "off"
            }
          },
          "mappings": [],
          "thresholds": {
            "mode": "absolute",
            "steps": [
              {
                "color": "green",
                "value": null
              },
              {
                "color": "red",
                "value": 80
              }
            ]
          },
          "unit": "s"
        },
        "overrides": []
      },
      "gridPos": {
        "h": 8,
        "w": 6,
        "x": 12,
        "y": 68
      },
      "id": 59,
      "options": {
        "legend": {
          "calcs": [],
          "displayMode": "list",
          "placement": "bottom"
        },
        "tooltip": {
          "mode": "single"
        }
      },
      "targets": [
        {
          "exemplar": true,
          "expr": "cnp_pg_stat_replication_flush_lag_seconds{namespace=~\"$namespace\",pod=~\"$cluster-.*\"}",
          "instant": false,
          "interval": "",
          "legendFormat": "{{application_name}}",
          "refId": "A"
        }
      ],
      "title": "Flush Lag",
      "type": "timeseries"
    },
    {
      "datasource": null,
      "description": "",
      "fieldConfig": {
        "defaults": {
          "color": {
            "mode": "palette-classic"
          },
          "custom": {
            "axisLabel": "",
            "axisPlacement": "auto",
            "barAlignment": 0,
            "drawStyle": "line",
            "fillOpacity": 10,
            "gradientMode": "none",
            "hideFrom": {
              "legend": false,
              "tooltip": false,
              "viz": false
            },
            "lineInterpolation": "linear",
            "lineWidth": 1,
            "pointSize": 5,
            "scaleDistribution": {
              "type": "linear"
            },
            "showPoints": "never",
            "spanNulls": true,
            "stacking": {
              "group": "A",
              "mode": "none"
            },
            "thresholdsStyle": {
              "mode": "off"
            }
          },
          "mappings": [],
          "thresholds": {
            "mode": "absolute",
            "steps": [
              {
                "color": "green",
                "value": null
              },
              {
                "color": "red",
                "value": 80
              }
            ]
          },
          "unit": "s"
        },
        "overrides": []
      },
      "gridPos": {
        "h": 8,
        "w": 6,
        "x": 18,
        "y": 68
      },
      "id": 20,
      "options": {
        "legend": {
          "calcs": [],
          "displayMode": "list",
          "placement": "bottom"
        },
        "tooltip": {
          "mode": "single"
        }
      },
      "targets": [
        {
          "exemplar": true,
          "expr": "cnp_pg_stat_replication_replay_lag_seconds{namespace=~\"$namespace\",pod=~\"$cluster-.*\"}",
          "interval": "",
          "legendFormat": "{{application_name}}",
          "refId": "A"
        }
      ],
      "title": "Replay Lag",
      "type": "timeseries"
    }
  ],
  "refresh": "5s",
  "schemaVersion": 31,
  "style": "dark",
  "tags": [],
  "templating": {
    "list": [
      {
        "allValue": null,
        "current": {
          "selected": false,
          "text": "default",
          "value": "default"
        },
        "datasource": null,
        "definition": "cnp_collector_up",
        "description": null,
        "error": null,
        "hide": 0,
        "includeAll": false,
        "label": null,
        "multi": false,
        "name": "namespace",
        "options": [],
        "query": {
          "query": "cnp_collector_up",
          "refId": "StandardVariableQuery"
        },
        "refresh": 1,
        "regex": "/namespace=\"(?<text>[^\"]+)|chip=\"(?<value>[^\"]+)/g",
        "skipUrlSync": false,
        "sort": 0,
        "type": "query"
      },
      {
        "allValue": null,
        "current": {
          "selected": false,
          "text": "cnp-playground",
          "value": "cnp-playground"
        },
        "datasource": null,
        "definition": "cnp_collector_up",
        "description": null,
        "error": null,
        "hide": 0,
        "includeAll": false,
        "label": null,
        "multi": false,
        "name": "cluster",
        "options": [],
        "query": {
          "query": "cnp_collector_up",
          "refId": "StandardVariableQuery"
        },
        "refresh": 1,
        "regex": "/cluster=\"(?<text>[^\"]+)|chip=\"(?<value>[^\"]+)/g",
        "skipUrlSync": false,
        "sort": 1,
        "type": "query"
      }
    ]
  },
  "time": {
    "from": "now-3h",
    "to": "now"
  },
  "timepicker": {
    "nowDelay": ""
  },
  "timezone": "",
  "title": "Cloud Native PostgreSQL",
  "uid": "z7FCA4Nnk",
  "version": 2
}
